notify_send_py/__init__.py
notify_send_py/notify_send_py.py
notify_send_py/notify3/__init__.py
notify_send_py/notify3/notify3.py
notify_send.py-1.2.7.dist-info/entry_points.txt
notify_send.py-1.2.7.dist-info/LICENSE
notify_send.py-1.2.7.dist-info/LICENSE_notify2
notify_send.py-1.2.7.dist-info/WHEEL
notify_send.py-1.2.7.dist-info/METADATA
notify_send.py-1.2.7.dist-info/RECORD
