Metadata-Version: 2.1
Name: notify-send.py
Version: 1.2.7
Summary: Script and module for sending desktop notifications
Home-page: https://github.com/phuhl/notify-send.py
License: UNKNOWN
Author: Philipp Uhl
Author-email: git@ph-uhl.com
Classifier: License :: OSI Approved :: MIT License
Requires-Dist: dbus-python
Requires-Dist: pygobject
Requires-Dist: flit ; extra == "dev"
Requires-Dist: pygments ; extra == "dev"
Provides-Extra: dev
